{"constants":[{"id":"constant-1","name":"QTEST_TOKEN","hidden":true,"value":""},{"id":"constant-2","name":"ManagerURL","hidden":false,"value":""}],"actions":[{"id":"action-1","name":"UpdateQTestWithResults","description":null,"code":"/*\n * trigger name: UpdateQTestWithResults\n * call source: any and all Result Parser rules via emitEvent()\n * payload example:\n        {\n          \"projectId\": \"5\",\n          \"testcycle\": \"555555\",\n          \"logs\": [\n            {\n              \"status\": \"passed\",\n              \"name\": \"Test 1 Name\",\n              \"attachments\": [],\n              \"exe_start_date\": \"2020-10-30T14:56:22.357Z\",\n              \"exe_end_date\": \"2020-10-30T14:56:22.357Z\",\n              \"automation_content\": \"uniquely identfied string\",\n              \"module_names\": [\n                \"TEST CYCLE FOLDER NAME\"\n              ],\n              \"test_step_logs\": [\n                {\n                  \"description\": \"Step 1 description\",\n                  \"expected_result\": \"Step 1 expected\",\n                  \"actual_result\": \"Step 1 result\",\n                  \"order\": 1,\n                  \"status\": \"passed\"\n                },\n                {\n                  \"description\": \"Step 2 description\",\n                  \"expected_result\": \"Step 2 expected\",\n                  \"actual_result\": \"Step 2 result\",\n                  \"order\": 2,\n                  \"status\": \"passed\"\n                },\n                {\n                  \"description\": \"Step 3 description\",\n                  \"expected_result\": \"Step 3 expected\",\n                  \"actual_result\": \"Step 3 result\",\n                  \"order\": 3,\n                  \"status\": \"passed\"\n                }\n                }\n              ]\n            }\n          ]\n        }\n * constants:\n *  QTEST_TOKEN: the qTest user bearer token from the API/SDK section of the 'Resources' area\n        Ex. 02e74731-2f6e-4b95-b928-1596a68881e2\n *  ManagerURL: the base qTest Manager domain with no protocol information, https is expected by the script\n        Ex. demo.qtestnet.com\n * outputs: standardized construct to be consumed by the qTest auto-test-logs API\n * external documentation: https://api.qasymphony.com/#/test-log/submitAutomationTestLogs2\n * Pulse events called (optional): ChatOpsEvent, CheckProcessingQueue\n */\n\n        const axios = require('axios');\n        const { Webhooks } = require('@qasymphony/pulse-sdk');\n        \n        exports.handler = async function ({ event: body, constants, triggers }, context, callback) {\n            function emitEvent(name, payload) {\n                const t = triggers && triggers.find(tr => tr.name === name);\n                if (t) return new Webhooks().invoke(t, payload);\n            }\n            let queueId = 0;\n            \n            console.log(`[INFO]: About to process ${body.logs.length} results...`);\n            emitEvent('ChatOpsEvent', { message: `[INFO]: About to process ${body.logs.length} results...`});\n        \n            let standardHeaders = {\n                'Content-Type': 'application/json',\n                'Authorization': `bearer ${constants.QTEST_TOKEN}`\n            }\n        \n            // Axios interceptor for global error handling\n            axios.interceptors.response.use(\n                response => response,\n                error => {\n                    console.error(error);\n                    return Promise.reject(error);\n                }\n            );\n        \n            async function createLogsAndTCs() {\n                let opts = {\n                    url: 'https://' + constants.ManagerURL + '/api/v3/projects/' + body.projectId + '/auto-test-logs?type=automation',\n                    method: 'post',\n                    headers: standardHeaders,\n                    data: {\n                        test_cycle: body.testcycle,\n                        test_logs: body.logs\n                    }\n                };\n        \n                try {\n                    const response = await axios(opts);\n                    if (response.data.type == 'AUTOMATION_TEST_LOG') {\n                        queueId = response.data.id;\n                        emitEvent('ChatOpsEvent', { message: '[INFO]: Results queued successfully for id: ' + response.data.id});\n                        console.log('[INFO]: Results queued successfully for id: ' + response.data.id);\n                        emitEvent('CheckProcessingQueue', {'queueId': queueId});\n                    } else {\n                        emitEvent('ChatOpsEvent', { message: 'Unable to upload test results.' });\n                        console.error('[ERROR]: Unable to upload test results. See logs for details.');\n                        emitEvent('ChatOpsEvent', { message: '[ERROR]: ' + JSON.stringify(response.data) });\n                    }\n                } catch (error) {\n                    if (error.response) {\n                        console.error('[ERROR]: qTest API', error.response.status, error.response.data);\n                    } else {\n                        console.error(error);\n                    }\n                }\n            };\n        \n            await createLogsAndTCs();\n        }"},{"id":"action-2","name":"Tosca_Results_Parser","description":null,"code":"const { Webhooks } = require('@qasymphony/pulse-sdk');\n\nexports.handler = function ({ event: body, constants, triggers }, context, callback) {\n    function emitEvent(name, payload) {\n        let t = triggers.find(t => t.name === name);\n        return t ? new Webhooks().invoke(t, payload) : console.error(`[ERROR]: (emitEvent) Webhook named '${name}' not found.`);\n    }\n\n    let payload = body;\n    let projectId = payload.projectId;\n    let cycleId = payload.testcycle;\n    let testLogs = [];\n\n    let testResults = Buffer.from(payload.result, 'base64').toString('utf8');\n\n    let parseString = require('xml2js').parseString;\n    let startTime = '';\n    let endTime = '';\n    let lastEndTime = 0;\n\n    parseString(testResults, {\n        preserveChildrenOrder: true,\n        explicitArray: false,\n        explicitChildren: false,\n        emptyTag: \"...\"\n    }, function (err, result) {\n        if (err) {\n            emitEvent('ChatOpsEvent', { Error: \"Unexpected Error Parsing XML Document: \" + err });\n            console.log(err);\n        } else {\n            let processTestSuite = function (testsuite) {\n                lastEndTime = 0;\n                let suiteName = testsuite.$.name;\n                console.log('Suite Name: ' + suiteName);\n                let testcases = Array.isArray(testsuite.testcase) ? testsuite.testcase : [testsuite.testcase];\n                testcases.forEach(function (testcase) {\n                    let classArray = [];\n                    classArray = testcase.$.name.replace('=>', ':').split(':');\n                    let depth = classArray.length;\n                    let className = classArray[(depth - 1)];\n                    let moduleNames = classArray.slice(0, depth - 1).map(folder => folder.trim());\n                    if (moduleNames.length === 0) {\n                        moduleNames.push(suiteName);\n                    }\n                    console.log('Case Name: ' + className);\n                    let classStatus = 'passed';\n                    startTime = lastEndTime === 0 ? new Date(Date.parse(testsuite.$.timestamp)).toISOString() : lastEndTime;\n                    const caseTime = parseFloat(testcase.$.time) || 0;\n                    let interim = new Date(Date.parse(startTime)).getSeconds() + caseTime;\n                    endTime = new Date(Date.parse(startTime)).setSeconds(interim);\n                    endTime = new Date(endTime).toISOString();\n\n                    let note = '';\n                    let stack = '';\n                    let processFailure = function (failure) {\n                        if (failure) {\n                            const attr = failure.$ || {};\n                            const fType = attr.type || 'Failure';\n                            const fMsg = attr.message || 'No message';\n                            note = fType + ': ' + fMsg;\n                            stack = failure._ != null ? String(failure._) : '';\n                            classStatus = 'failed';\n                        }\n                    };\n\n                    let testFailure = Array.isArray(testcase.failure) ? testcase.failure : [testcase.failure];\n                    testFailure.forEach(processFailure);\n\n                    let testError = Array.isArray(testcase.error) ? testcase.error : [testcase.error];\n                    testError.forEach(function (error) {\n                        if (error) {\n                            const attr = error.$ || {};\n                            note = attr.message || 'Error';\n                            classStatus = 'failed';\n                        }\n                    });\n\n                    let testSkipped = Array.isArray(testcase.skipped) ? testcase.skipped : [testcase.skipped];\n                    testSkipped.forEach(function (skipped) {\n                        if (skipped) {\n                            classStatus = 'skipped';\n                        }\n                    });\n\n                    console.log(classStatus);\n\n                    let testLog = {\n                        status: classStatus,\n                        name: className,\n                        attachments: [],\n                        note: note,\n                        exe_start_date: startTime,\n                        exe_end_date: endTime,\n                        automation_content: htmlEntities(className),\n                        module_names: moduleNames\n                    };\n\n                    if (stack !== '') {\n                        testLog.attachments.push({\n                            name: `${className}.txt`,\n                            data: Buffer.from(stack).toString(\"base64\"),\n                            content_type: \"text/plain\"\n                        });\n                    }\n                    testLogs.push(testLog);\n                    lastEndTime = endTime;\n                });\n            };\n\n            if (result.testsuites) {\n                let testsuites = Array.isArray(result.testsuites['testsuite']) ? result.testsuites['testsuite'] : [result.testsuites['testsuite']];\n                testsuites.forEach(processTestSuite);\n            } else {\n                console.log('Test Suites collection doesn\\'t exist, checking for singular test suite.');\n                let testsuite = result.testsuite;\n                if (testsuite) {\n                    processTestSuite(testsuite);\n                } else {\n                    console.log('No Test Suite found, exiting.');\n                }\n            }\n        }\n    });\n\n    let formattedResults = {\n        \"projectId\": projectId,\n        \"testcycle\": cycleId,\n        \"logs\": testLogs\n    };\n\n    emitEvent('UpdateQTestWithResults', formattedResults);\n};\n\nfunction htmlEntities(str) {\n    return String(str).replace(/&/g, '&amp;').replace(/</g, '&lt;').replace(/>/g, '&gt;').replace(/\"/g, '&quot;');\n}"},{"id":"action-3","name":"ChatOpsEvent","description":null,"code":"const PulseSdk = require('@qasymphony/pulse-sdk');\nconst request = require('request');\nconst xml2js = require('xml2js');\n\n// DO NOT EDIT exported \"handler\" function is the entrypoint\nexports.handler = async function({ event, constants, triggers }, context, callback) {\n  // TODO implement\n}\n"}],"triggers":[{"id":"trigger-1","name":"GitHub_Actions_Pipeline"},{"id":"trigger-2","name":"UpdateQTestWithResults"},{"id":"trigger-3","name":"ChatOpsEvent"}],"rules":[{"id":"rule-4","name":"Parse_Tosca_Results_From_GitHub","active":true,"triggerId":"trigger-1","actionIds":["action-2"],"tags":[]},{"id":"rule-5","name":"UpdateQTestWithResults","active":true,"triggerId":"trigger-2","actionIds":["action-1"],"tags":[]},{"id":"rule-6","name":"ChatOpsEvent","active":true,"triggerId":"trigger-3","actionIds":["action-3"],"tags":[]}]}
